{"count":"485","earthquakes":[{"src":"us","eqid":"2012jvau","timedate":"2012-12-31 21:37:35","lat":"-6.9486","lon":"154.6561","magnitude":"4.6","depth":"51.00","region":"Bougainville region, Papua New Guinea"},{"src":"us","eqid":"c000ehy6","timedate":"2012-12-31 20:02:04","lat":"-61.5964","lon":"154.2878","magnitude":"5.2","depth":"10.00","region":"Balleny Islands region"},{"src":"us","eqid":"2012jvar","timedate":"2012-12-31 15:33:53","lat":"14.0829","lon":"-92.1843","magnitude":"4.4","depth":"62.40","region":"offshore Guatemala"},{"src":"us","eqid":"2012jvar","timedate":"2012-12-31 15:33:53","lat":"14.0829","lon":"-92.1843","magnitude":"4.4","depth":"62.40","region":"offshore Guatemala"},{"src":"us","eqid":"2012jvaq","timedate":"2012-12-31 15:11:59","lat":"52.7877","lon":"171.4308","magnitude":"4.5","depth":"48.40","region":"Near Islands, Aleutian Islands, Alaska"},{"src":"us","eqid":"2012jvap","timedate":"2012-12-31 15:00:16","lat":"16.6253","lon":"-98.7552","magnitude":"4.0","depth":"35.00","region":"Guerrero, Mexico"},{"src":"us","eqid":"2012jvap","timedate":"2012-12-31 15:00:16","lat":"16.6253","lon":"-98.7552","magnitude":"4.0","depth":"35.00","region":"Guerrero, Mexico"},{"src":"us","eqid":"2012jvan","timedate":"2012-12-31 14:21:28","lat":"14.3062","lon":"-92.0272","magnitude":"4.5","depth":"62.70","region":"offshore Guatemala"},{"src":"us","eqid":"2012jvam","timedate":"2012-12-31 14:15:23","lat":"-7.6833","lon":"128.4022","magnitude":"4.7","depth":"82.20","region":"Kepulauan Barat Daya, Indonesia"},{"src":"us","eqid":"c000ehuy","timedate":"2012-12-31 09:36:01","lat":"37.4750","lon":"143.6794","magnitude":"4.8","depth":"34.30","region":"off the east coast of Honshu, Japan"},{"src":"us","eqid":"c000ehur","timedate":"2012-12-31 08:50:07","lat":"-3.2371","lon":"86.4539","magnitude":"5.0","depth":"9.80","region":"South Indian Ocean"},{"src":"us","eqid":"c000ehun","timedate":"2012-12-31 08:46:20","lat":"-11.1933","lon":"-77.4891","magnitude":"4.9","depth":"69.80","region":"near the coast of central Peru"},{"src":"us","eqid":"c000ehtx","timedate":"2012-12-31 06:01:25","lat":"-7.0241","lon":"120.2789","magnitude":"4.6","depth":"594.40","region":"Flores Sea"},{"src":"us","eqid":"c000eht6","timedate":"2012-12-31 01:45:00","lat":"35.2709","lon":"-36.2773","magnitude":"4.7","depth":"10.10","region":"northern Mid-Atlantic Ridge"},{"src":"us","eqid":"c000eht6","timedate":"2012-12-31 01:45:00","lat":"35.2709","lon":"-36.2773","magnitude":"4.7","depth":"10.10","region":"northern Mid-Atlantic Ridge"},{"src":"us","eqid":"c000ehsy","timedate":"2012-12-31 01:15:18","lat":"15.0582","lon":"-92.1402","magnitude":"5.0","depth":"113.90","region":"Chiapas, Mexico"},{"src":"us","eqid":"c000ehrp","timedate":"2012-12-30 20:49:29","lat":"-12.8778","lon":"-70.9742","magnitude":"5.2","depth":"41.50","region":"central Peru"},{"src":"us","eqid":"c000ehr2","timedate":"2012-12-30 19:25:54","lat":"-2.0259","lon":"100.7654","magnitude":"4.7","depth":"62.40","region":"Kepulauan Mentawai region, Indonesia"},{"src":"us","eqid":"2012juam","timedate":"2012-12-30 16:58:41","lat":"-21.7972","lon":"-176.6847","magnitude":"4.7","depth":"216.60","region":"Fiji region"},{"src":"us","eqid":"2012juam","timedate":"2012-12-30 16:58:41","lat":"-21.7972","lon":"-176.6847","magnitude":"4.7","depth":"216.60","region":"Fiji region"},{"src":"us","eqid":"2012jual","timedate":"2012-12-30 16:03:26","lat":"23.4689","lon":"120.9519","magnitude":"4.8","depth":"3.70","region":"Taiwan"},{"src":"us","eqid":"c000ehn7","timedate":"2012-12-30 12:21:23","lat":"14.5255","lon":"-92.9274","magnitude":"5.2","depth":"35.50","region":"offshore Chiapas, Mexico"},{"src":"us","eqid":"c000ehn1","timedate":"2012-12-30 11:33:41","lat":"1.5739","lon":"126.6903","magnitude":"5.1","depth":"58.60","region":"Molucca Sea"},{"src":"us","eqid":"c000ehmg","timedate":"2012-12-30 08:16:44","lat":"24.2655","lon":"91.8902","magnitude":"4.3","depth":"30.50","region":"India-Bangladesh border region"},{"src":"us","eqid":"c000ehm0","timedate":"2012-12-30 07:56:50","lat":"-7.0512","lon":"105.2199","magnitude":"5.0","depth":"34.90","region":"Java, Indonesia"},{"src":"us","eqid":"c000ehm0","timedate":"2012-12-30 07:56:50","lat":"-7.0512","lon":"105.2199","magnitude":"5.0","depth":"34.90","region":"Java, Indonesia"},{"src":"us","eqid":"c000ehlt","timedate":"2012-12-30 06:44:41","lat":"-60.9299","lon":"-36.9667","magnitude":"5.2","depth":"10.00","region":"Scotia Sea"},{"src":"us","eqid":"c000ehlt","timedate":"2012-12-30 06:44:41","lat":"-60.9299","lon":"-36.9667","magnitude":"5.2","depth":"10.00","region":"Scotia Sea"},{"src":"us","eqid":"c000ehl1","timedate":"2012-12-30 02:54:51","lat":"52.0474","lon":"-171.0298","magnitude":"4.5","depth":"53.00","region":"Fox Islands, Aleutian Islands, Alaska"},{"src":"us","eqid":"c000ehjm","timedate":"2012-12-29 23:05:26","lat":"37.0558","lon":"141.1822","magnitude":"5.2","depth":"58.30","region":"near the east coast of Honshu, Japan"},{"src":"us","eqid":"c000ehjp","timedate":"2012-12-29 23:01:21","lat":"0.9946","lon":"125.6074","magnitude":"4.2","depth":"34.80","region":"Molucca Sea"},{"src":"us","eqid":"c000ehjg","timedate":"2012-12-29 22:43:55","lat":"-6.6028","lon":"129.8569","magnitude":"4.5","depth":"168.50","region":"Banda Sea"},{"src":"us","eqid":"c000ehjg","timedate":"2012-12-29 22:43:55","lat":"-6.6028","lon":"129.8569","magnitude":"4.5","depth":"168.50","region":"Banda Sea"},{"src":"us","eqid":"c000ehj0","timedate":"2012-12-29 21:47:28","lat":"2.1295","lon":"-97.5872","magnitude":"4.5","depth":"10.00","region":"west of the Galapagos Islands"},{"src":"us","eqid":"c000ehil","timedate":"2012-12-29 21:37:01","lat":"1.5675","lon":"-98.2408","magnitude":"4.5","depth":"10.00","region":"west of the Galapagos Islands"},{"src":"us","eqid":"c000ehhv","timedate":"2012-12-29 20:29:52","lat":"-6.6100","lon":"129.8654","magnitude":"4.6","depth":"162.50","region":"Banda Sea"},{"src":"us","eqid":"c000ehhr","timedate":"2012-12-29 20:13:05","lat":"36.6834","lon":"71.1163","magnitude":"4.4","depth":"239.50","region":"Hindu Kush region, Afghanistan"},{"src":"us","eqid":"c000ehh7","timedate":"2012-12-29 18:42:03","lat":"52.5410","lon":"-169.4703","magnitude":"4.2","depth":"6.50","region":"Fox Islands, Aleutian Islands, Alaska"},{"src":"us","eqid":"c000ehh7","timedate":"2012-12-29 18:42:03","lat":"52.5410","lon":"-169.4703","magnitude":"4.2","depth":"6.50","region":"Fox Islands, Aleutian Islands, Alaska"},{"src":"us","eqid":"c000ehgp","timedate":"2012-12-29 17:50:53","lat":"35.6974","lon":"70.5453","magnitude":"5.8","depth":"115.90","region":"Hindu Kush region, Afghanistan"},{"src":"us","eqid":"c000ehgg","timedate":"2012-12-29 17:15:10","lat":"4.1053","lon":"126.8366","magnitude":"4.9","depth":"56.60","region":"Kepulauan Talaud, Indonesia"},{"src":"us","eqid":"c000ehg2","timedate":"2012-12-29 14:59:36","lat":"38.7574","lon":"142.0958","magnitude":"5.5","depth":"33.60","region":"near the east coast of Honshu, Japan"},{"src":"us","eqid":"c000ehg2","timedate":"2012-12-29 14:59:36","lat":"38.7574","lon":"142.0958","magnitude":"5.5","depth":"33.60","region":"near the east coast of Honshu, Japan"},{"src":"us","eqid":"c000ehf0","timedate":"2012-12-29 10:29:43","lat":"51.8690","lon":"-173.1885","magnitude":"4.3","depth":"45.80","region":"Andreanof Islands, Aleutian Islands, Alaska"},{"src":"us","eqid":"c000ehen","timedate":"2012-12-29 09:53:06","lat":"10.7235","lon":"-86.2636","magnitude":"4.4","depth":"35.10","region":"off the coast of Costa Rica"},{"src":"us","eqid":"c000ehen","timedate":"2012-12-29 09:53:06","lat":"10.7235","lon":"-86.2636","magnitude":"4.4","depth":"35.10","region":"off the coast of Costa Rica"},{"src":"us","eqid":"c000ehed","timedate":"2012-12-29 08:33:19","lat":"-6.5824","lon":"129.8714","magnitude":"4.6","depth":"143.40","region":"Banda Sea"},{"src":"us","eqid":"c000ehe8","timedate":"2012-12-29 07:59:15","lat":"-3.3531","lon":"148.7224","magnitude":"5.5","depth":"10.20","region":"Bismarck Sea"},{"src":"us","eqid":"c000ehe5","timedate":"2012-12-29 07:56:00","lat":"-3.3607","lon":"148.6531","magnitude":"5.0","depth":"9.90","region":"Bismarck Sea"},{"src":"us","eqid":"c000ehdw","timedate":"2012-12-29 07:19:32","lat":"37.0653","lon":"141.1660","magnitude":"5.1","depth":"40.40","region":"near the east coast of Honshu, Japan"},{"src":"us","eqid":"c000ehdf","timedate":"2012-12-29 06:04:16","lat":"-19.8990","lon":"-69.2160","magnitude":"4.3","depth":"101.30","region":"Tarapaca, Chile"},{"src":"us","eqid":"c000ehd0","timedate":"2012-12-29 04:38:28","lat":"-26.0407","lon":"-177.2562","magnitude":"4.8","depth":"105.70","region":"south of the Fiji Islands"},{"src":"us","eqid":"c000ehck","timedate":"2012-12-29 04:01:50","lat":"11.2905","lon":"-86.9828","magnitude":"4.4","depth":"65.80","region":"near the coast of Nicaragua"},{"src":"us","eqid":"c000ehbz","timedate":"2012-12-29 02:43:31","lat":"14.2731","lon":"-91.1787","magnitude":"4.1","depth":"64.80","region":"Guatemala"},{"src":"us","eqid":"c000ehbz","timedate":"2012-12-29 02:43:31","lat":"14.2731","lon":"-91.1787","magnitude":"4.1","depth":"64.80","region":"Guatemala"},{"src":"us","eqid":"c000ehbq","timedate":"2012-12-29 01:57:41","lat":"-11.4197","lon":"-76.7834","magnitude":"4.6","depth":"99.40","region":"central Peru"},{"src":"us","eqid":"c000eh40","timedate":"2012-12-28 17:32:17","lat":"-0.2450","lon":"122.9399","magnitude":"5.5","depth":"104.40","region":"Sulawesi, Indonesia"},{"src":"us","eqid":"c000eh31","timedate":"2012-12-28 16:23:49","lat":"13.7823","lon":"-88.9038","magnitude":"4.7","depth":"181.10","region":"El Salvador"},{"src":"us","eqid":"c000eh2v","timedate":"2012-12-28 16:11:22","lat":"38.1337","lon":"143.9661","magnitude":"4.8","depth":"17.20","region":"off the east coast of Honshu, Japan"},{"src":"us","eqid":"c000eh2n","timedate":"2012-12-28 15:04:40","lat":"1.6935","lon":"89.5502","magnitude":"4.6","depth":"14.10","region":"North Indian Ocean"},{"src":"us","eqid":"c000eh2l","timedate":"2012-12-28 14:27:10","lat":"-35.3800","lon":"-103.5936","magnitude":"4.7","depth":"10.00","region":"southeast of Easter Island"},{"src":"us","eqid":"c000eh2d","timedate":"2012-12-28 14:05:36","lat":"13.8307","lon":"-91.4297","magnitude":"4.3","depth":"60.60","region":"offshore Guatemala"},{"src":"us","eqid":"c000eh27","timedate":"2012-12-28 13:50:34","lat":"-29.5602","lon":"-71.2903","magnitude":"4.7","depth":"40.30","region":"Coquimbo, Chile"},{"src":"us","eqid":"c000eh22","timedate":"2012-12-28 13:42:34","lat":"55.6093","lon":"164.7981","magnitude":"5.5","depth":"35.80","region":"Komandorskiye Ostrova, Russia region"},{"src":"us","eqid":"c000eh22","timedate":"2012-12-28 13:42:34","lat":"55.6093","lon":"164.7981","magnitude":"5.5","depth":"35.80","region":"Komandorskiye Ostrova, Russia region"},{"src":"us","eqid":"c000eh20","timedate":"2012-12-28 13:27:41","lat":"13.8048","lon":"-91.2456","magnitude":"4.6","depth":"66.70","region":"offshore Guatemala"},{"src":"us","eqid":"c000eh20","timedate":"2012-12-28 13:27:41","lat":"13.8048","lon":"-91.2456","magnitude":"4.6","depth":"66.70","region":"offshore Guatemala"},{"src":"us","eqid":"c000eh1y","timedate":"2012-12-28 13:04:16","lat":"52.6995","lon":"-169.6001","magnitude":"4.4","depth":"7.90","region":"Fox Islands, Aleutian Islands, Alaska"},{"src":"us","eqid":"c000eh1j","timedate":"2012-12-28 12:30:40","lat":"46.5034","lon":"151.2005","magnitude":"4.6","depth":"99.70","region":"Kuril Islands"},{"src":"us","eqid":"c000eh0t","timedate":"2012-12-28 11:07:50","lat":"-7.2554","lon":"124.4015","magnitude":"4.3","depth":"540.10","region":"Banda Sea"},{"src":"us","eqid":"c000eh0d","timedate":"2012-12-28 10:35:46","lat":"-29.6630","lon":"-176.3101","magnitude":"5.1","depth":"9.90","region":"Kermadec Islands region"},{"src":"us","eqid":"c000eh0d","timedate":"2012-12-28 10:35:46","lat":"-29.6630","lon":"-176.3101","magnitude":"5.1","depth":"9.90","region":"Kermadec Islands region"},{"src":"us","eqid":"c000eh09","timedate":"2012-12-28 10:13:15","lat":"-6.6089","lon":"129.8298","magnitude":"4.5","depth":"150.70","region":"Banda Sea"},{"src":"us","eqid":"c000egzu","timedate":"2012-12-28 09:38:59","lat":"-29.7744","lon":"-177.1397","magnitude":"4.5","depth":"9.70","region":"Kermadec Islands, New Zealand"},{"src":"us","eqid":"c000egzu","timedate":"2012-12-28 09:38:59","lat":"-29.7744","lon":"-177.1397","magnitude":"4.5","depth":"9.70","region":"Kermadec Islands, New Zealand"},{"src":"us","eqid":"c000egzm","timedate":"2012-12-28 08:50:11","lat":"-31.3316","lon":"-65.0287","magnitude":"4.6","depth":"34.10","region":"Cordoba, Argentina"},{"src":"us","eqid":"c000egyi","timedate":"2012-12-28 05:21:07","lat":"0.5268","lon":"126.1780","magnitude":"4.8","depth":"21.00","region":"Molucca Sea"},{"src":"us","eqid":"c000egw5","timedate":"2012-12-27 23:20:55","lat":"38.1945","lon":"21.9397","magnitude":"4.1","depth":"12.60","region":"Greece"},{"src":"us","eqid":"c000egp2","timedate":"2012-12-27 16:33:59","lat":"-12.3617","lon":"-14.8743","magnitude":"5.2","depth":"9.50","region":"southern Mid-Atlantic Ridge"},{"src":"us","eqid":"c000egnh","timedate":"2012-12-27 15:32:17","lat":"-10.8065","lon":"-168.8632","magnitude":"4.9","depth":"15.30","region":"Samoa Islands region"},{"src":"us","eqid":"c000egnh","timedate":"2012-12-27 15:32:17","lat":"-10.8065","lon":"-168.8632","magnitude":"4.9","depth":"15.30","region":"Samoa Islands region"},{"src":"us","eqid":"c000egmq","timedate":"2012-12-27 13:41:40","lat":"12.0757","lon":"123.6518","magnitude":"4.7","depth":"34.60","region":"Masbate region, Philippines"},{"src":"us","eqid":"c000egmk","timedate":"2012-12-27 13:05:03","lat":"24.3325","lon":"-109.0529","magnitude":"4.7","depth":"10.00","region":"Gulf of California"},{"src":"us","eqid":"c000egm0","timedate":"2012-12-27 11:37:54","lat":"-31.2436","lon":"-68.4607","magnitude":"4.6","depth":"80.90","region":"San Juan, Argentina"},{"src":"us","eqid":"c000eglj","timedate":"2012-12-27 10:41:13","lat":"14.0682","lon":"-92.3514","magnitude":"4.4","depth":"47.50","region":"offshore Guatemala"},{"src":"us","eqid":"c000eglj","timedate":"2012-12-27 10:41:13","lat":"14.0682","lon":"-92.3514","magnitude":"4.4","depth":"47.50","region":"offshore Guatemala"},{"src":"us","eqid":"c000egla","timedate":"2012-12-27 09:50:18","lat":"-21.3869","lon":"-178.9519","magnitude":"4.6","depth":"564.40","region":"Fiji region"},{"src":"us","eqid":"c000egkq","timedate":"2012-12-27 09:42:02","lat":"-18.2972","lon":"-173.5542","magnitude":"5.3","depth":"39.70","region":"Tonga"},{"src":"us","eqid":"c000egkq","timedate":"2012-12-27 09:42:02","lat":"-18.2972","lon":"-173.5542","magnitude":"5.3","depth":"39.70","region":"Tonga"},{"src":"us","eqid":"c000egjv","timedate":"2012-12-27 06:57:09","lat":"-30.2412","lon":"-111.8235","magnitude":"4.8","depth":"10.00","region":"Easter Island region"},{"src":"us","eqid":"c000egjv","timedate":"2012-12-27 06:57:09","lat":"-30.2412","lon":"-111.8235","magnitude":"4.8","depth":"10.00","region":"Easter Island region"},{"src":"us","eqid":"c000egjb","timedate":"2012-12-27 05:36:12","lat":"12.9663","lon":"-57.9746","magnitude":"5.3","depth":"14.00","region":"North Atlantic Ocean"},{"src":"us","eqid":"c000eghx","timedate":"2012-12-27 03:03:01","lat":"-35.7888","lon":"-73.0216","magnitude":"4.7","depth":"11.60","region":"offshore Maule, Chile"},{"src":"us","eqid":"c000egha","timedate":"2012-12-27 01:18:08","lat":"-35.8179","lon":"-73.1526","magnitude":"4.8","depth":"18.10","region":"offshore Maule, Chile"},{"src":"us","eqid":"c000eggc","timedate":"2012-12-27 00:37:10","lat":"-35.7653","lon":"-73.2744","magnitude":"5.1","depth":"22.20","region":"offshore Maule, Chile"},{"src":"us","eqid":"c000egin","timedate":"2012-12-26 23:36:32","lat":"28.3351","lon":"142.0727","magnitude":"4.5","depth":"42.30","region":"Bonin Islands, Japan region"},{"src":"us","eqid":"c000egnf","timedate":"2012-12-26 23:01:57","lat":"-56.1914","lon":"-144.5646","magnitude":"5.5","depth":"13.20","region":"Pacific-Antarctic Ridge"},{"src":"us","eqid":"c000eg9q","timedate":"2012-12-26 20:24:26","lat":"-10.4319","lon":"-13.1700","magnitude":"5.3","depth":"9.20","region":"Ascension Island region"},{"src":"us","eqid":"c000eg8c","timedate":"2012-12-26 19:08:03","lat":"0.9128","lon":"98.7394","magnitude":"5.0","depth":"77.30","region":"Nias region, Indonesia"},{"src":"us","eqid":"2012jqaq","timedate":"2012-12-26 16:50:49","lat":"-6.0526","lon":"155.0346","magnitude":"4.4","depth":"159.10","region":"Bougainville region, Papua New Guinea"},{"src":"us","eqid":"2012jqap","timedate":"2012-12-26 16:12:40","lat":"-7.9070","lon":"107.3727","magnitude":"4.6","depth":"46.30","region":"Java, Indonesia"},{"src":"us","eqid":"2012jqan","timedate":"2012-12-26 15:20:43","lat":"22.7711","lon":"95.9618","magnitude":"4.4","depth":"34.20","region":"Myanmar"},{"src":"us","eqid":"c000eg66","timedate":"2012-12-26 13:59:46","lat":"22.7720","lon":"95.8895","magnitude":"4.9","depth":"20.50","region":"Myanmar"},{"src":"us","eqid":"c000eg66","timedate":"2012-12-26 13:59:46","lat":"22.7720","lon":"95.8895","magnitude":"4.9","depth":"20.50","region":"Myanmar"},{"src":"us","eqid":"c000eg5v","timedate":"2012-12-26 13:17:56","lat":"-37.2813","lon":"-73.3632","magnitude":"5.5","depth":"24.70","region":"Bio-Bio, Chile"},{"src":"us","eqid":"c000eg52","timedate":"2012-12-26 09:46:42","lat":"-21.0983","lon":"-68.5738","magnitude":"4.5","depth":"116.60","region":"Antofagasta, Chile"},{"src":"us","eqid":"c000eg3g","timedate":"2012-12-26 05:17:26","lat":"-24.2279","lon":"-178.9853","magnitude":"5.1","depth":"457.10","region":"south of the Fiji Islands"},{"src":"us","eqid":"c000eg1h","timedate":"2012-12-26 02:58:24","lat":"-20.6281","lon":"-178.5702","magnitude":"4.9","depth":"589.90","region":"Fiji region"},{"src":"us","eqid":"c000eg1h","timedate":"2012-12-26 02:58:24","lat":"-20.6281","lon":"-178.5702","magnitude":"4.9","depth":"589.90","region":"Fiji region"},{"src":"us","eqid":"c000eg10","timedate":"2012-12-26 02:24:33","lat":"-5.9601","lon":"147.3032","magnitude":"5.3","depth":"95.50","region":"eastern New Guinea region, Papua New Guinea"},{"src":"us","eqid":"c000eg0v","timedate":"2012-12-26 02:06:36","lat":"23.9752","lon":"122.5406","magnitude":"4.9","depth":"22.00","region":"Taiwan region"},{"src":"us","eqid":"c000eg06","timedate":"2012-12-25 23:09:32","lat":"39.5552","lon":"74.8015","magnitude":"4.6","depth":"10.70","region":"southern Xinjiang, China"},{"src":"us","eqid":"c000eg05","timedate":"2012-12-25 22:55:51","lat":"42.5051","lon":"40.9159","magnitude":"4.5","depth":"9.80","region":"Black Sea, offshore Georgia"},{"src":"us","eqid":"c000eg04","timedate":"2012-12-25 22:44:34","lat":"42.4412","lon":"41.0194","magnitude":"5.3","depth":"13.80","region":"Black Sea, offshore Georgia"},{"src":"us","eqid":"c000eg04","timedate":"2012-12-25 22:44:34","lat":"42.4412","lon":"41.0194","magnitude":"5.3","depth":"13.80","region":"Black Sea, offshore Georgia"},{"src":"us","eqid":"c000efz4","timedate":"2012-12-25 17:36:29","lat":"28.4022","lon":"66.4236","magnitude":"5.1","depth":"10.00","region":"Pakistan"},{"src":"us","eqid":"c000efyu","timedate":"2012-12-25 17:08:16","lat":"31.9427","lon":"137.9391","magnitude":"4.8","depth":"372.50","region":"Izu Islands, Japan region"},{"src":"us","eqid":"c000efve","timedate":"2012-12-25 08:46:32","lat":"-7.9167","lon":"101.2688","magnitude":"5.1","depth":"28.60","region":"southwest of Sumatra, Indonesia"},{"src":"us","eqid":"c000efve","timedate":"2012-12-25 08:46:32","lat":"-7.9167","lon":"101.2688","magnitude":"5.1","depth":"28.60","region":"southwest of Sumatra, Indonesia"},{"src":"us","eqid":"c000efup","timedate":"2012-12-25 07:34:42","lat":"1.1016","lon":"125.5119","magnitude":"5.3","depth":"56.70","region":"Molucca Sea"},{"src":"ak","eqid":"10624575","timedate":"2012-12-25 03:43:32","lat":"61.3128","lon":"-147.4456","magnitude":"4.4","depth":"26.80","region":"Southern Alaska"},{"src":"ak","eqid":"10624575","timedate":"2012-12-25 03:43:32","lat":"61.3128","lon":"-147.4456","magnitude":"4.4","depth":"26.80","region":"Southern Alaska"},{"src":"us","eqid":"c000eft0","timedate":"2012-12-25 03:30:32","lat":"-6.5499","lon":"130.0312","magnitude":"4.4","depth":"169.60","region":"Banda Sea"},{"src":"us","eqid":"c000efsl","timedate":"2012-12-25 01:07:33","lat":"-22.4059","lon":"-12.6500","magnitude":"4.9","depth":"10.00","region":"southern Mid-Atlantic Ridge"},{"src":"us","eqid":"c000efs4","timedate":"2012-12-24 23:47:22","lat":"52.0611","lon":"-176.1583","magnitude":"4.5","depth":"116.40","region":"Andreanof Islands, Aleutian Islands, Alaska"},{"src":"us","eqid":"c000efrf","timedate":"2012-12-24 23:24:50","lat":"-55.6751","lon":"147.0902","magnitude":"5.0","depth":"10.00","region":"west of Macquarie Island"},{"src":"us","eqid":"c000efr4","timedate":"2012-12-24 22:41:15","lat":"36.7246","lon":"26.6101","magnitude":"4.2","depth":"9.80","region":"Dodecanese Islands, Greece"},{"src":"us","eqid":"c000efr4","timedate":"2012-12-24 22:41:15","lat":"36.7246","lon":"26.6101","magnitude":"4.2","depth":"9.80","region":"Dodecanese Islands, Greece"},{"src":"ak","eqid":"10624283","timedate":"2012-12-24 17:28:25","lat":"61.2434","lon":"-150.7752","magnitude":"4.0","depth":"57.10","region":"Southern Alaska"},{"src":"us","eqid":"c000efkj","timedate":"2012-12-24 12:58:19","lat":"4.1249","lon":"126.7219","magnitude":"5.1","depth":"21.60","region":"Kepulauan Talaud, Indonesia"},{"src":"us","eqid":"c000efkj","timedate":"2012-12-24 12:58:19","lat":"4.1249","lon":"126.7219","magnitude":"5.1","depth":"21.60","region":"Kepulauan Talaud, Indonesia"},{"src":"us","eqid":"c000efjz","timedate":"2012-12-24 12:12:37","lat":"-28.9985","lon":"-71.5069","magnitude":"5.2","depth":"32.40","region":"offshore Atacama, Chile"},{"src":"us","eqid":"c000efjx","timedate":"2012-12-24 12:01:19","lat":"-10.8822","lon":"165.9866","magnitude":"4.9","depth":"62.70","region":"Santa Cruz Islands"},{"src":"us","eqid":"c000efiw","timedate":"2012-12-24 10:13:34","lat":"54.9887","lon":"161.9113","magnitude":"4.6","depth":"21.80","region":"near the east coast of the Kamchatka Peninsula, Russia"},{"src":"us","eqid":"c000efig","timedate":"2012-12-24 09:05:55","lat":"51.5652","lon":"-176.8827","magnitude":"4.4","depth":"54.40","region":"Andreanof Islands, Aleutian Islands, Alaska"},{"src":"us","eqid":"c000efhx","timedate":"2012-12-24 07:54:09","lat":"55.0040","lon":"161.8911","magnitude":"5.2","depth":"14.20","region":"near the east coast of the Kamchatka Peninsula, Russia"},{"src":"us","eqid":"c000efh3","timedate":"2012-12-24 06:30:12","lat":"-20.5179","lon":"169.2748","magnitude":"4.5","depth":"23.30","region":"Vanuatu"},{"src":"us","eqid":"c000efgd","timedate":"2012-12-24 05:31:34","lat":"-17.9309","lon":"-69.9403","magnitude":"4.8","depth":"92.20","region":"southern Peru"},{"src":"us","eqid":"c000efg7","timedate":"2012-12-24 05:08:37","lat":"-33.9674","lon":"-72.0895","magnitude":"4.7","depth":"12.20","region":"offshore Libertador O'Higgins, Chile"},{"src":"us","eqid":"2012jnac","timedate":"2012-12-24 04:38:33","lat":"-9.4462","lon":"110.1831","magnitude":"4.9","depth":"35.90","region":"south of Java, Indonesia"},{"src":"us","eqid":"c000efeq","timedate":"2012-12-23 23:41:40","lat":"53.1677","lon":"-166.7945","magnitude":"4.2","depth":"48.60","region":"Fox Islands, Aleutian Islands, Alaska"},{"src":"us","eqid":"c000efeq","timedate":"2012-12-23 23:41:40","lat":"53.1677","lon":"-166.7945","magnitude":"4.2","depth":"48.60","region":"Fox Islands, Aleutian Islands, Alaska"},{"src":"us","eqid":"c000efe3","timedate":"2012-12-23 22:19:32","lat":"-18.9964","lon":"168.3902","magnitude":"4.7","depth":"15.20","region":"Vanuatu"},{"src":"us","eqid":"c000efbf","timedate":"2012-12-23 19:08:40","lat":"50.6838","lon":"-129.6433","magnitude":"4.2","depth":"14.30","region":"Vancouver Island, Canada region"},{"src":"us","eqid":"c000ef8l","timedate":"2012-12-23 13:31:39","lat":"42.4175","lon":"41.0637","magnitude":"5.5","depth":"10.00","region":"Black Sea, offshore Georgia"},{"src":"us","eqid":"c000ef8g","timedate":"2012-12-23 12:59:48","lat":"36.4982","lon":"70.2482","magnitude":"4.0","depth":"217.30","region":"Hindu Kush region, Afghanistan"},{"src":"us","eqid":"c000ef8g","timedate":"2012-12-23 12:59:48","lat":"36.4982","lon":"70.2482","magnitude":"4.0","depth":"217.30","region":"Hindu Kush region, Afghanistan"},{"src":"us","eqid":"c000ef8c","timedate":"2012-12-23 12:52:23","lat":"4.1712","lon":"126.6336","magnitude":"5.2","depth":"31.90","region":"Kepulauan Talaud, Indonesia"},{"src":"us","eqid":"c000ef7m","timedate":"2012-12-23 11:01:16","lat":"14.4868","lon":"-92.2626","magnitude":"4.3","depth":"86.90","region":"offshore Guatemala"},{"src":"us","eqid":"c000ef76","timedate":"2012-12-23 09:47:27","lat":"-12.1371","lon":"167.0575","magnitude":"4.5","depth":"246.50","region":"Santa Cruz Islands"},{"src":"us","eqid":"c000ef6g","timedate":"2012-12-23 07:12:33","lat":"38.3416","lon":"45.0029","magnitude":"4.1","depth":"10.00","region":"northwestern Iran"},{"src":"us","eqid":"c000ef64","timedate":"2012-12-23 06:38:57","lat":"38.5044","lon":"44.8448","magnitude":"5.2","depth":"10.50","region":"Turkey-Iran border region"},{"src":"us","eqid":"c000ef5y","timedate":"2012-12-23 06:13:06","lat":"24.2854","lon":"121.4658","magnitude":"4.6","depth":"9.40","region":"Taiwan"},{"src":"us","eqid":"c000ef5q","timedate":"2012-12-23 05:52:13","lat":"-7.7525","lon":"117.2346","magnitude":"4.5","depth":"291.50","region":"Bali Sea"},{"src":"us","eqid":"c000ef5m","timedate":"2012-12-23 05:29:30","lat":"36.2011","lon":"70.0461","magnitude":"4.4","depth":"110.60","region":"Hindu Kush region, Afghanistan"},{"src":"us","eqid":"c000ef5l","timedate":"2012-12-23 05:11:45","lat":"-17.1367","lon":"168.4497","magnitude":"4.6","depth":"206.80","region":"Vanuatu"},{"src":"us","eqid":"c000ef3k","timedate":"2012-12-23 00:29:55","lat":"-13.0799","lon":"167.1131","magnitude":"5.2","depth":"211.00","region":"Vanuatu"},{"src":"us","eqid":"c000ef2c","timedate":"2012-12-22 22:32:42","lat":"1.5761","lon":"126.6121","magnitude":"4.3","depth":"37.50","region":"Molucca Sea"},{"src":"us","eqid":"c000ef1t","timedate":"2012-12-22 22:04:35","lat":"15.8302","lon":"-98.3177","magnitude":"4.3","depth":"5.40","region":"offshore Oaxaca, Mexico"},{"src":"ci","eqid":"15267105","timedate":"2012-12-22 21:37:45","lat":"32.9990","lon":"-116.2397","magnitude":"4.0","depth":"4.40","region":"Southern California"},{"src":"us","eqid":"c000eexu","timedate":"2012-12-22 18:07:17","lat":"19.1724","lon":"121.0881","magnitude":"5.1","depth":"29.00","region":"Babuyan Islands region, Philippines"},{"src":"us","eqid":"c000eewi","timedate":"2012-12-22 16:41:44","lat":"22.4300","lon":"94.7533","magnitude":"5.5","depth":"126.60","region":"Myanmar"},{"src":"us","eqid":"c000eewi","timedate":"2012-12-22 16:41:44","lat":"22.4300","lon":"94.7533","magnitude":"5.5","depth":"126.60","region":"Myanmar"},{"src":"us","eqid":"c000eew1","timedate":"2012-12-22 16:02:44","lat":"-6.0452","lon":"-76.5211","magnitude":"4.9","depth":"42.50","region":"northern Peru"},{"src":"us","eqid":"c000eetk","timedate":"2012-12-22 11:07:18","lat":"-4.5000","lon":"125.2012","magnitude":"4.5","depth":"453.70","region":"Banda Sea"},{"src":"us","eqid":"c000eeti","timedate":"2012-12-22 10:58:28","lat":"-7.1344","lon":"129.0496","magnitude":"4.7","depth":"178.20","region":"Kepulauan Babar, Indonesia"},{"src":"us","eqid":"c000eesf","timedate":"2012-12-22 07:53:01","lat":"-20.3042","lon":"169.5346","magnitude":"4.9","depth":"133.00","region":"Vanuatu"},{"src":"us","eqid":"c000eerw","timedate":"2012-12-22 07:00:41","lat":"16.7563","lon":"-93.6296","magnitude":"4.4","depth":"168.90","region":"Chiapas, Mexico"},{"src":"us","eqid":"c000eerz","timedate":"2012-12-22 06:43:39","lat":"-12.5600","lon":"-76.8200","magnitude":"4.2","depth":"51.00","region":"near the coast of central Peru"},{"src":"us","eqid":"c000eerz","timedate":"2012-12-22 06:43:39","lat":"-12.5600","lon":"-76.8200","magnitude":"4.2","depth":"51.00","region":"near the coast of central Peru"},{"src":"us","eqid":"c000eerm","timedate":"2012-12-22 06:20:23","lat":"41.3687","lon":"142.6202","magnitude":"4.7","depth":"34.90","region":"Hokkaido, Japan region"},{"src":"us","eqid":"c000eeri","timedate":"2012-12-22 06:15:32","lat":"33.5540","lon":"132.1164","magnitude":"4.6","depth":"65.60","region":"Shikoku, Japan"},{"src":"us","eqid":"c000eer4","timedate":"2012-12-22 05:54:08","lat":"13.9394","lon":"-91.3173","magnitude":"4.6","depth":"70.00","region":"offshore Guatemala"},{"src":"us","eqid":"c000eeql","timedate":"2012-12-22 05:30:31","lat":"-25.7814","lon":"-67.0581","magnitude":"4.2","depth":"20.10","region":"Catamarca, Argentina"},{"src":"us","eqid":"c000eeq8","timedate":"2012-12-22 04:42:37","lat":"49.8626","lon":"155.1446","magnitude":"5.1","depth":"117.20","region":"Kuril Islands"},{"src":"us","eqid":"c000eeq8","timedate":"2012-12-22 04:42:37","lat":"49.8626","lon":"155.1446","magnitude":"5.1","depth":"117.20","region":"Kuril Islands"},{"src":"us","eqid":"c000eepi","timedate":"2012-12-22 03:50:03","lat":"5.2341","lon":"94.2665","magnitude":"5.2","depth":"10.00","region":"northern Sumatra, Indonesia"},{"src":"us","eqid":"c000eepb","timedate":"2012-12-22 03:24:33","lat":"21.9797","lon":"121.6031","magnitude":"4.4","depth":"9.70","region":"Taiwan region"},{"src":"us","eqid":"c000eemn","timedate":"2012-12-22 02:04:22","lat":"-2.6538","lon":"119.9794","magnitude":"4.9","depth":"35.00","region":"Sulawesi, Indonesia"},{"src":"us","eqid":"c000eek3","timedate":"2012-12-21 22:28:09","lat":"-14.3824","lon":"167.2596","magnitude":"6.8","depth":"207.90","region":"Vanuatu"},{"src":"us","eqid":"c000eefg","timedate":"2012-12-21 19:24:57","lat":"27.5721","lon":"-111.6305","magnitude":"4.4","depth":"25.40","region":"Gulf of California"},{"src":"us","eqid":"c000ee9s","timedate":"2012-12-21 14:43:37","lat":"29.8424","lon":"142.2157","magnitude":"5.0","depth":"20.30","region":"Izu Islands, Japan region"},{"src":"us","eqid":"c000ee9s","timedate":"2012-12-21 14:43:37","lat":"29.8424","lon":"142.2157","magnitude":"5.0","depth":"20.30","region":"Izu Islands, Japan region"},{"src":"us","eqid":"c000ee74","timedate":"2012-12-21 09:26:52","lat":"-20.1510","lon":"-176.3218","magnitude":"4.5","depth":"234.70","region":"Fiji region"},{"src":"us","eqid":"c000ee68","timedate":"2012-12-21 08:07:18","lat":"38.6019","lon":"141.9118","magnitude":"5.0","depth":"35.30","region":"near the east coast of Honshu, Japan"},{"src":"us","eqid":"c000ee5z","timedate":"2012-12-21 07:30:44","lat":"0.9890","lon":"98.7779","magnitude":"4.5","depth":"62.80","region":"Nias region, Indonesia"},{"src":"us","eqid":"c000ee5q","timedate":"2012-12-21 07:05:10","lat":"13.4763","lon":"-91.7856","magnitude":"4.3","depth":"35.50","region":"offshore Guatemala"},{"src":"us","eqid":"c000ee5f","timedate":"2012-12-21 06:23:09","lat":"-15.3650","lon":"-173.0125","magnitude":"4.6","depth":"40.30","region":"Tonga"},{"src":"us","eqid":"c000ee4m","timedate":"2012-12-21 04:49:06","lat":"52.2293","lon":"157.7812","magnitude":"4.8","depth":"132.30","region":"Kamchatka Peninsula, Russia"},{"src":"us","eqid":"c000ee2a","timedate":"2012-12-21 01:45:18","lat":"-20.7346","lon":"-174.1045","magnitude":"4.9","depth":"30.70","region":"Tonga"},{"src":"us","eqid":"c000ee2a","timedate":"2012-12-21 01:45:18","lat":"-20.7346","lon":"-174.1045","magnitude":"4.9","depth":"30.70","region":"Tonga"},{"src":"us","eqid":"c000edtz","timedate":"2012-12-20 21:47:30","lat":"0.5465","lon":"126.2327","magnitude":"5.6","depth":"31.20","region":"Molucca Sea"},{"src":"us","eqid":"c000edtz","timedate":"2012-12-20 21:47:30","lat":"0.5465","lon":"126.2327","magnitude":"5.6","depth":"31.20","region":"Molucca Sea"},{"src":"us","eqid":"c000edp4","timedate":"2012-12-20 19:38:46","lat":"-20.7734","lon":"-174.0887","magnitude":"5.0","depth":"45.10","region":"Tonga"},{"src":"us","eqid":"c000edgq","timedate":"2012-12-20 15:31:15","lat":"37.0874","lon":"141.1468","magnitude":"4.8","depth":"58.60","region":"near the east coast of Honshu, Japan"},{"src":"us","eqid":"c000edg2","timedate":"2012-12-20 15:00:18","lat":"-22.8050","lon":"-63.7063","magnitude":"4.7","depth":"525.20","region":"Salta, Argentina"},{"src":"us","eqid":"c000edg2","timedate":"2012-12-20 15:00:18","lat":"-22.8050","lon":"-63.7063","magnitude":"4.7","depth":"525.20","region":"Salta, Argentina"},{"src":"us","eqid":"c000edej","timedate":"2012-12-20 13:38:05","lat":"-7.1032","lon":"129.2383","magnitude":"4.8","depth":"162.10","region":"Kepulauan Babar, Indonesia"},{"src":"us","eqid":"c000ede8","timedate":"2012-12-20 13:00:42","lat":"26.7263","lon":"76.3031","magnitude":"4.0","depth":"10.00","region":"Rajasthan, India"},{"src":"us","eqid":"c000edcf","timedate":"2012-12-20 10:54:27","lat":"42.1791","lon":"142.6223","magnitude":"4.7","depth":"9.80","region":"Hokkaido, Japan region"},{"src":"us","eqid":"c000edaz","timedate":"2012-12-20 09:31:40","lat":"37.9095","lon":"143.8563","magnitude":"4.8","depth":"33.50","region":"off the east coast of Honshu, Japan"},{"src":"us","eqid":"c000edb2","timedate":"2012-12-20 09:03:19","lat":"53.0799","lon":"170.8873","magnitude":"4.6","depth":"27.70","region":"Near Islands, Aleutian Islands, Alaska"},{"src":"us","eqid":"c000ed8l","timedate":"2012-12-20 07:18:02","lat":"55.2426","lon":"161.6712","magnitude":"4.3","depth":"66.10","region":"near the east coast of the Kamchatka Peninsula, Russia"},{"src":"us","eqid":"c000ed8c","timedate":"2012-12-20 07:01:12","lat":"-6.5975","lon":"129.9872","magnitude":"4.4","depth":"163.40","region":"Banda Sea"},{"src":"us","eqid":"c000ed7b","timedate":"2012-12-20 05:56:04","lat":"22.9248","lon":"96.1035","magnitude":"4.7","depth":"9.70","region":"Myanmar"},{"src":"us","eqid":"c000ed5r","timedate":"2012-12-20 03:17:04","lat":"37.4669","lon":"143.7652","magnitude":"4.9","depth":"27.90","region":"off the east coast of Honshu, Japan"},{"src":"us","eqid":"c000ed53","timedate":"2012-12-20 02:11:19","lat":"-7.4941","lon":"128.6773","magnitude":"4.6","depth":"151.40","region":"Kepulauan Barat Daya, Indonesia"},{"src":"us","eqid":"c000ed3f","timedate":"2012-12-19 22:40:15","lat":"39.6546","lon":"143.2937","magnitude":"4.6","depth":"39.80","region":"off the east coast of Honshu, Japan"},{"src":"us","eqid":"2012jiam","timedate":"2012-12-19 16:08:08","lat":"40.6581","lon":"139.1529","magnitude":"4.7","depth":"34.80","region":"near the west coast of Honshu, Japan"},{"src":"us","eqid":"c000eci7","timedate":"2012-12-19 16:02:20","lat":"-20.4727","lon":"-174.3318","magnitude":"5.0","depth":"9.90","region":"Tonga"},{"src":"us","eqid":"2012jial","timedate":"2012-12-19 15:19:53","lat":"-52.3156","lon":"139.3895","magnitude":"4.7","depth":"10.00","region":"west of Macquarie Island"},{"src":"us","eqid":"2012jiaj","timedate":"2012-12-19 14:00:19","lat":"9.0547","lon":"123.9821","magnitude":"4.6","depth":"91.30","region":"Negros - Cebu region, Philippines"},{"src":"us","eqid":"c000ecg1","timedate":"2012-12-19 11:51:52","lat":"-19.0088","lon":"-175.6601","magnitude":"4.9","depth":"226.50","region":"Tonga"},{"src":"us","eqid":"c000ecfv","timedate":"2012-12-19 11:14:52","lat":"51.9239","lon":"173.6783","magnitude":"4.7","depth":"25.70","region":"Near Islands, Aleutian Islands, Alaska"},{"src":"us","eqid":"c000ecfh","timedate":"2012-12-19 10:25:57","lat":"-28.9237","lon":"61.9928","magnitude":"4.8","depth":"10.00","region":"Southwest Indian Ridge"},{"src":"us","eqid":"c000ecel","timedate":"2012-12-19 08:03:57","lat":"-34.4328","lon":"-109.2693","magnitude":"4.6","depth":"10.00","region":"southern East Pacific Rise"},{"src":"us","eqid":"c000ecbb","timedate":"2012-12-19 00:23:29","lat":"6.8330","lon":"-73.0257","magnitude":"4.4","depth":"155.30","region":"northern Colombia"},{"src":"us","eqid":"c000ecas","timedate":"2012-12-18 23:56:55","lat":"-17.9325","lon":"168.4422","magnitude":"4.8","depth":"131.30","region":"Vanuatu"},{"src":"us","eqid":"c000ec9v","timedate":"2012-12-18 22:54:09","lat":"-7.2504","lon":"144.0609","magnitude":"4.9","depth":"33.50","region":"near the south coast of New Guinea, Papua New Guinea"},{"src":"us","eqid":"c000ec0s","timedate":"2012-12-18 19:57:11","lat":"52.3737","lon":"-132.1422","magnitude":"4.3","depth":"17.30","region":"Queen Charlotte Islands, Canada region"},{"src":"us","eqid":"c000ec0s","timedate":"2012-12-18 19:57:11","lat":"52.3737","lon":"-132.1422","magnitude":"4.3","depth":"17.30","region":"Queen Charlotte Islands, Canada region"},{"src":"us","eqid":"c000ebyt","timedate":"2012-12-18 18:36:24","lat":"36.6784","lon":"142.0137","magnitude":"5.1","depth":"33.50","region":"off the east coast of Honshu, Japan"},{"src":"us","eqid":"c000ebye","timedate":"2012-12-18 18:13:51","lat":"12.8457","lon":"-88.7424","magnitude":"4.6","depth":"74.70","region":"offshore El Salvador"},{"src":"us","eqid":"2012jhap","timedate":"2012-12-18 14:26:09","lat":"33.1301","lon":"84.4036","magnitude":"4.0","depth":"10.00","region":"western Xizang"},{"src":"us","eqid":"c000ebtj","timedate":"2012-12-18 11:51:58","lat":"25.3543","lon":"96.5776","magnitude":"4.6","depth":"39.60","region":"Myanmar"},{"src":"us","eqid":"c000ebsw","timedate":"2012-12-18 10:49:41","lat":"-9.0721","lon":"111.3580","magnitude":"4.5","depth":"13.20","region":"south of Java, Indonesia"},{"src":"us","eqid":"c000ebsq","timedate":"2012-12-18 10:26:02","lat":"38.6370","lon":"140.0060","magnitude":"4.6","depth":"77.20","region":"eastern Honshu, Japan"},{"src":"us","eqid":"c000ebrt","timedate":"2012-12-18 08:27:05","lat":"-6.2554","lon":"120.6840","magnitude":"4.7","depth":"40.10","region":"Flores Sea"},{"src":"us","eqid":"c000ebrl","timedate":"2012-12-18 08:12:24","lat":"13.0281","lon":"-89.9915","magnitude":"5.1","depth":"57.50","region":"offshore El Salvador"},{"src":"us","eqid":"c000ebrh","timedate":"2012-12-18 07:58:52","lat":"52.1236","lon":"-171.4587","magnitude":"4.2","depth":"54.10","region":"Fox Islands, Aleutian Islands, Alaska"},{"src":"us","eqid":"c000ebrh","timedate":"2012-12-18 07:58:52","lat":"52.1236","lon":"-171.4587","magnitude":"4.2","depth":"54.10","region":"Fox Islands, Aleutian Islands, Alaska"},{"src":"us","eqid":"c000ebps","timedate":"2012-12-18 01:47:14","lat":"16.2243","lon":"-95.6154","magnitude":"4.4","depth":"49.70","region":"Oaxaca, Mexico"},{"src":"us","eqid":"c000ebpq","timedate":"2012-12-18 01:38:28","lat":"16.4174","lon":"-95.4004","magnitude":"4.8","depth":"60.90","region":"Oaxaca, Mexico"},{"src":"us","eqid":"c000ebpm","timedate":"2012-12-18 01:32:46","lat":"19.3538","lon":"95.7841","magnitude":"4.6","depth":"41.00","region":"Myanmar"},{"src":"us","eqid":"c000ebmf","timedate":"2012-12-17 22:52:23","lat":"37.7658","lon":"143.5970","magnitude":"5.0","depth":"47.30","region":"off the east coast of Honshu, Japan"},{"src":"us","eqid":"c000ebcg","timedate":"2012-12-17 17:46:48","lat":"-3.9682","lon":"-104.0375","magnitude":"5.1","depth":"15.70","region":"central East Pacific Rise"},{"src":"us","eqid":"c000ebc8","timedate":"2012-12-17 17:41:36","lat":"-4.1074","lon":"-104.4160","magnitude":"5.1","depth":"35.70","region":"central East Pacific Rise"},{"src":"us","eqid":"2012jgai","timedate":"2012-12-17 13:13:09","lat":"37.7211","lon":"143.8415","magnitude":"4.5","depth":"35.00","region":"off the east coast of Honshu, Japan"},{"src":"us","eqid":"c000eb81","timedate":"2012-12-17 11:28:37","lat":"-30.9935","lon":"-176.5889","magnitude":"4.7","depth":"41.40","region":"Kermadec Islands region"},{"src":"us","eqid":"c000eb6k","timedate":"2012-12-17 09:16:28","lat":"-0.7085","lon":"123.8371","magnitude":"6.1","depth":"18.50","region":"Sulawesi, Indonesia"},{"src":"us","eqid":"c000eaz1","timedate":"2012-12-17 00:28:55","lat":"49.7494","lon":"155.9524","magnitude":"5.6","depth":"38.90","region":"Kuril Islands"},{"src":"us","eqid":"c000eavl","timedate":"2012-12-16 22:46:11","lat":"-33.7624","lon":"-71.4325","magnitude":"4.8","depth":"54.90","region":"Valparaiso, Chile"},{"src":"us","eqid":"c000eav8","timedate":"2012-12-16 21:50:29","lat":"18.2062","lon":"146.8433","magnitude":"4.4","depth":"53.60","region":"Pagan region, Northern Mariana Islands"},{"src":"us","eqid":"c000eauj","timedate":"2012-12-16 20:39:24","lat":"-19.8127","lon":"-69.5099","magnitude":"4.9","depth":"108.50","region":"Tarapaca, Chile"},{"src":"us","eqid":"2012jfa2","timedate":"2012-12-16 16:49:05","lat":"5.9050","lon":"-78.0246","magnitude":"4.6","depth":"10.00","region":"south of Panama"},{"src":"us","eqid":"2012jfa1","timedate":"2012-12-16 16:10:09","lat":"-6.6311","lon":"154.8930","magnitude":"4.6","depth":"91.10","region":"Bougainville region, Papua New Guinea"},{"src":"us","eqid":"c000ear0","timedate":"2012-12-16 15:52:01","lat":"14.1903","lon":"146.7879","magnitude":"5.3","depth":"24.40","region":"Rota region, Northern Mariana Islands"},{"src":"us","eqid":"2012jfau","timedate":"2012-12-16 13:12:28","lat":"-8.3954","lon":"117.7434","magnitude":"4.3","depth":"45.10","region":"Sumbawa region, Indonesia"},{"src":"us","eqid":"2012jfau","timedate":"2012-12-16 13:12:28","lat":"-8.3954","lon":"117.7434","magnitude":"4.3","depth":"45.10","region":"Sumbawa region, Indonesia"},{"src":"us","eqid":"c000eanw","timedate":"2012-12-16 11:46:27","lat":"-24.7760","lon":"-70.1580","magnitude":"4.8","depth":"39.20","region":"Antofagasta, Chile"},{"src":"us","eqid":"c000eanc","timedate":"2012-12-16 10:29:32","lat":"39.9843","lon":"77.8969","magnitude":"4.9","depth":"8.60","region":"southern Xinjiang, China"},{"src":"us","eqid":"c000eanb","timedate":"2012-12-16 10:23:42","lat":"10.5253","lon":"-86.1584","magnitude":"4.6","depth":"44.40","region":"off the coast of Costa Rica"},{"src":"us","eqid":"c000ean6","timedate":"2012-12-16 10:07:12","lat":"14.7523","lon":"-91.3828","magnitude":"5.2","depth":"113.50","region":"Guatemala"},{"src":"us","eqid":"c000eamz","timedate":"2012-12-16 09:17:17","lat":"52.7217","lon":"-167.0689","magnitude":"4.6","depth":"21.30","region":"Fox Islands, Aleutian Islands, Alaska"},{"src":"us","eqid":"c000eami","timedate":"2012-12-16 08:04:41","lat":"29.1031","lon":"140.7688","magnitude":"4.8","depth":"99.60","region":"Izu Islands, Japan region"},{"src":"us","eqid":"c000ealj","timedate":"2012-12-16 07:03:13","lat":"35.2147","lon":"27.6911","magnitude":"4.0","depth":"34.80","region":"Dodecanese Islands, Greece"},{"src":"us","eqid":"c000eakw","timedate":"2012-12-16 06:04:17","lat":"-10.7094","lon":"166.1011","magnitude":"4.7","depth":"153.70","region":"Santa Cruz Islands"},{"src":"us","eqid":"c000eakq","timedate":"2012-12-16 05:52:08","lat":"-33.6063","lon":"-179.2981","magnitude":"4.7","depth":"41.50","region":"south of the Kermadec Islands"},{"src":"us","eqid":"c000eajf","timedate":"2012-12-16 03:06:53","lat":"14.0946","lon":"-91.9013","magnitude":"4.8","depth":"72.30","region":"offshore Guatemala"},{"src":"us","eqid":"c000eaj7","timedate":"2012-12-16 02:30:55","lat":"18.2150","lon":"146.9730","magnitude":"4.8","depth":"55.50","region":"Pagan region, Northern Mariana Islands"},{"src":"us","eqid":"c000eai7","timedate":"2012-12-15 23:46:46","lat":"-24.0300","lon":"-67.1100","magnitude":"4.2","depth":"163.00","region":"Salta, Argentina"},{"src":"us","eqid":"c000eagf","timedate":"2012-12-15 21:23:44","lat":"37.6032","lon":"143.7840","magnitude":"4.8","depth":"34.10","region":"off the east coast of Honshu, Japan"},{"src":"us","eqid":"c000eacu","timedate":"2012-12-15 19:30:03","lat":"-4.7244","lon":"152.9635","magnitude":"6.0","depth":"55.80","region":"New Britain region, Papua New Guinea"},{"src":"us","eqid":"c000eacp","timedate":"2012-12-15 19:16:50","lat":"-3.5048","lon":"100.4524","magnitude":"4.9","depth":"15.10","region":"Kepulauan Mentawai region, Indonesia"},{"src":"us","eqid":"c000ea8h","timedate":"2012-12-15 13:03:27","lat":"13.2040","lon":"-89.8574","magnitude":"4.5","depth":"74.40","region":"offshore El Salvador"},{"src":"us","eqid":"c000ea8d","timedate":"2012-12-15 12:43:29","lat":"12.1342","lon":"-88.7001","magnitude":"5.0","depth":"34.60","region":"off the coast of El Salvador"},{"src":"us","eqid":"c000ea8d","timedate":"2012-12-15 12:43:29","lat":"12.1342","lon":"-88.7001","magnitude":"5.0","depth":"34.60","region":"off the coast of El Salvador"},{"src":"us","eqid":"c000ea7e","timedate":"2012-12-15 11:02:12","lat":"19.5338","lon":"-62.9410","magnitude":"4.3","depth":"23.20","region":"north of Anguilla, Leeward Islands"},{"src":"us","eqid":"c000ea7d","timedate":"2012-12-15 10:55:25","lat":"37.6024","lon":"143.7456","magnitude":"4.8","depth":"35.40","region":"off the east coast of Honshu, Japan"},{"src":"us","eqid":"c000ea70","timedate":"2012-12-15 08:53:35","lat":"-23.9763","lon":"-66.8168","magnitude":"4.5","depth":"204.90","region":"Jujuy, Argentina"},{"src":"us","eqid":"c000ea6f","timedate":"2012-12-15 07:33:14","lat":"-4.9240","lon":"153.3783","magnitude":"5.2","depth":"58.20","region":"New Ireland region, Papua New Guinea"},{"src":"us","eqid":"c000ea5r","timedate":"2012-12-15 05:46:15","lat":"36.7974","lon":"141.1277","magnitude":"4.8","depth":"45.30","region":"near the east coast of Honshu, Japan"},{"src":"us","eqid":"c000ea5j","timedate":"2012-12-15 04:49:30","lat":"52.3445","lon":"173.9648","magnitude":"5.9","depth":"29.90","region":"Near Islands, Aleutian Islands, Alaska"},{"src":"us","eqid":"c000ea5i","timedate":"2012-12-15 04:27:02","lat":"37.3486","lon":"141.2867","magnitude":"5.2","depth":"57.80","region":"near the east coast of Honshu, Japan"},{"src":"us","eqid":"c000ea5b","timedate":"2012-12-15 02:53:19","lat":"13.0954","lon":"-89.8514","magnitude":"4.4","depth":"66.00","region":"offshore El Salvador"},{"src":"us","eqid":"c000ea5b","timedate":"2012-12-15 02:53:19","lat":"13.0954","lon":"-89.8514","magnitude":"4.4","depth":"66.00","region":"offshore El Salvador"},{"src":"us","eqid":"c000ea4j","timedate":"2012-12-15 01:03:36","lat":"-8.6241","lon":"120.4166","magnitude":"4.5","depth":"126.40","region":"Flores region, Indonesia"},{"src":"us","eqid":"c000ea4g","timedate":"2012-12-15 00:40:42","lat":"55.4920","lon":"-163.5901","magnitude":"4.2","depth":"170.30","region":"Unimak Island region, Alaska"},{"src":"us","eqid":"c000ea3c","timedate":"2012-12-14 22:37:24","lat":"-6.2291","lon":"130.1823","magnitude":"4.8","depth":"133.90","region":"Banda Sea"},{"src":"us","eqid":"c000ea29","timedate":"2012-12-14 22:00:40","lat":"34.3202","lon":"23.9919","magnitude":"4.1","depth":"10.00","region":"Crete, Greece"},{"src":"us","eqid":"c000ea0n","timedate":"2012-12-14 20:37:19","lat":"38.6256","lon":"142.3347","magnitude":"4.8","depth":"53.90","region":"near the east coast of Honshu, Japan"},{"src":"us","eqid":"c000e9yi","timedate":"2012-12-14 19:18:57","lat":"13.0116","lon":"-89.9826","magnitude":"4.8","depth":"69.00","region":"offshore El Salvador"},{"src":"us","eqid":"c000e9wy","timedate":"2012-12-14 17:46:45","lat":"-5.2589","lon":"153.4126","magnitude":"5.1","depth":"36.70","region":"New Ireland region, Papua New Guinea"},{"src":"us","eqid":"c000e9vj","timedate":"2012-12-14 16:52:38","lat":"-15.3680","lon":"-178.1066","magnitude":"5.3","depth":"10.00","region":"Fiji region"},{"src":"us","eqid":"c000e9v8","timedate":"2012-12-14 16:16:21","lat":"-7.7974","lon":"105.7824","magnitude":"4.8","depth":"31.60","region":"Java, Indonesia"},{"src":"us","eqid":"c000e9st","timedate":"2012-12-14 10:50:15","lat":"31.2368","lon":"-119.6956","magnitude":"4.7","depth":"9.80","region":"off the west coast of Baja California"},{"src":"us","eqid":"c000e9sl","timedate":"2012-12-14 10:36:02","lat":"31.2130","lon":"-119.5599","magnitude":"6.3","depth":"11.30","region":"off the west coast of Baja California"},{"src":"us","eqid":"c000e9sa","timedate":"2012-12-14 09:55:44","lat":"-19.0288","lon":"169.5407","magnitude":"4.6","depth":"9.90","region":"Vanuatu"},{"src":"us","eqid":"c000e9r5","timedate":"2012-12-14 05:07:04","lat":"37.5221","lon":"143.7947","magnitude":"4.7","depth":"33.40","region":"off the east coast of Honshu, Japan"},{"src":"us","eqid":"c000e9qr","timedate":"2012-12-14 04:58:51","lat":"14.0122","lon":"-91.7643","magnitude":"5.1","depth":"45.90","region":"offshore Guatemala"},{"src":"us","eqid":"c000e9qr","timedate":"2012-12-14 04:58:51","lat":"14.0122","lon":"-91.7643","magnitude":"5.1","depth":"45.90","region":"offshore Guatemala"},{"src":"us","eqid":"c000e9qm","timedate":"2012-12-14 04:21:43","lat":"13.3929","lon":"-89.6941","magnitude":"4.2","depth":"69.10","region":"offshore El Salvador"},{"src":"us","eqid":"c000e9qk","timedate":"2012-12-14 04:15:23","lat":"13.9577","lon":"-92.0351","magnitude":"4.4","depth":"45.60","region":"offshore Guatemala"},{"src":"us","eqid":"c000e9qg","timedate":"2012-12-14 04:04:08","lat":"13.9564","lon":"-91.7409","magnitude":"5.2","depth":"45.60","region":"offshore Guatemala"},{"src":"us","eqid":"c000e9q1","timedate":"2012-12-14 02:34:53","lat":"-5.0175","lon":"152.9437","magnitude":"5.1","depth":"52.50","region":"New Britain region, Papua New Guinea"},{"src":"us","eqid":"c000e9pu","timedate":"2012-12-14 02:17:33","lat":"22.7509","lon":"95.9026","magnitude":"4.7","depth":"23.50","region":"Myanmar"},{"src":"us","eqid":"c000e9p2","timedate":"2012-12-14 01:22:05","lat":"37.4292","lon":"143.5469","magnitude":"4.9","depth":"39.80","region":"off the east coast of Honshu, Japan"},{"src":"us","eqid":"c000e9mt","timedate":"2012-12-13 23:03:38","lat":"80.7946","lon":"121.4507","magnitude":"5.7","depth":"9.90","region":"east of Severnaya Zemlya"},{"src":"us","eqid":"c000e9ky","timedate":"2012-12-13 21:39:26","lat":"41.1105","lon":"19.7927","magnitude":"4.5","depth":"10.10","region":"Albania"},{"src":"us","eqid":"c000e9kp","timedate":"2012-12-13 21:26:40","lat":"13.1400","lon":"-90.0042","magnitude":"5.5","depth":"13.00","region":"offshore El Salvador"},{"src":"us","eqid":"c000e9fk","timedate":"2012-12-13 17:20:26","lat":"9.0439","lon":"-84.0414","magnitude":"4.9","depth":"34.00","region":"Costa Rica"},{"src":"us","eqid":"c000e9fb","timedate":"2012-12-13 17:16:22","lat":"9.0981","lon":"-84.0662","magnitude":"5.0","depth":"37.30","region":"Costa Rica"},{"src":"us","eqid":"c000e9dn","timedate":"2012-12-13 15:16:11","lat":"-21.1047","lon":"-68.8577","magnitude":"4.3","depth":"140.40","region":"Tarapaca, Chile"},{"src":"us","eqid":"c000e9cc","timedate":"2012-12-13 11:56:06","lat":"35.5723","lon":"140.1926","magnitude":"4.6","depth":"62.60","region":"near the east coast of Honshu, Japan"},{"src":"us","eqid":"c000e9bd","timedate":"2012-12-13 10:02:43","lat":"23.4265","lon":"-44.7535","magnitude":"4.7","depth":"10.10","region":"northern Mid-Atlantic Ridge"},{"src":"us","eqid":"c000e972","timedate":"2012-12-13 00:53:32","lat":"-30.9282","lon":"-178.2524","magnitude":"5.5","depth":"64.90","region":"Kermadec Islands, New Zealand"},{"src":"us","eqid":"c000e8ib","timedate":"2012-12-12 06:54:33","lat":"10.0725","lon":"-84.3868","magnitude":"4.5","depth":"10.10","region":"Costa Rica"},{"src":"us","eqid":"c000e8hr","timedate":"2012-12-12 06:41:08","lat":"33.8711","lon":"141.2183","magnitude":"4.5","depth":"66.40","region":"off the east coast of Honshu, Japan"},{"src":"us","eqid":"c000e8fe","timedate":"2012-12-12 01:44:24","lat":"-19.6031","lon":"-176.2306","magnitude":"5.0","depth":"35.00","region":"Fiji region"},{"src":"us","eqid":"c000e8fe","timedate":"2012-12-12 01:44:24","lat":"-19.6031","lon":"-176.2306","magnitude":"5.0","depth":"35.00","region":"Fiji region"},{"src":"us","eqid":"c000e8en","timedate":"2012-12-12 00:19:37","lat":"37.0035","lon":"141.1830","magnitude":"4.8","depth":"14.70","region":"near the east coast of Honshu, Japan"},{"src":"us","eqid":"c000e8ec","timedate":"2012-12-11 23:28:04","lat":"30.6725","lon":"140.0954","magnitude":"4.8","depth":"136.00","region":"Izu Islands, Japan region"},{"src":"us","eqid":"c000e8e8","timedate":"2012-12-11 23:16:19","lat":"-18.9901","lon":"167.7904","magnitude":"5.1","depth":"10.00","region":"Vanuatu"},{"src":"us","eqid":"2012jaaq","timedate":"2012-12-11 16:28:06","lat":"-33.9636","lon":"-179.7074","magnitude":"4.3","depth":"77.30","region":"south of the Kermadec Islands"},{"src":"us","eqid":"c000e8jt","timedate":"2012-12-11 15:30:17","lat":"18.7106","lon":"-81.3065","magnitude":"4.1","depth":"9.60","region":"Cayman Islands region"},{"src":"us","eqid":"c000e828","timedate":"2012-12-11 12:18:20","lat":"-19.0942","lon":"167.6241","magnitude":"5.2","depth":"28.20","region":"Vanuatu region"},{"src":"us","eqid":"c000e821","timedate":"2012-12-11 12:14:56","lat":"12.6299","lon":"-88.4905","magnitude":"4.4","depth":"88.60","region":"offshore El Salvador"},{"src":"us","eqid":"c000e80y","timedate":"2012-12-11 10:32:04","lat":"24.0052","lon":"121.6612","magnitude":"4.4","depth":"27.00","region":"Taiwan"},{"src":"us","eqid":"c000e80p","timedate":"2012-12-11 10:28:23","lat":"13.8519","lon":"-91.5539","magnitude":"4.4","depth":"35.10","region":"offshore Guatemala"},{"src":"us","eqid":"c000e7zt","timedate":"2012-12-11 08:02:02","lat":"13.9538","lon":"-92.1646","magnitude":"4.1","depth":"35.00","region":"offshore Guatemala"},{"src":"us","eqid":"c000e7ym","timedate":"2012-12-11 06:18:27","lat":"0.5948","lon":"126.2471","magnitude":"5.8","depth":"29.70","region":"Molucca Sea"},{"src":"us","eqid":"c000e7yh","timedate":"2012-12-11 05:37:02","lat":"14.5300","lon":"56.2314","magnitude":"4.8","depth":"10.00","region":"Owen Fracture Zone region"},{"src":"us","eqid":"c000e7y4","timedate":"2012-12-11 05:12:20","lat":"68.1355","lon":"-136.4082","magnitude":"5.1","depth":"9.90","region":"northern Yukon Territory, Canada"},{"src":"us","eqid":"c000e7up","timedate":"2012-12-10 23:56:20","lat":"13.9698","lon":"-91.4986","magnitude":"4.2","depth":"35.50","region":"offshore Guatemala"},{"src":"us","eqid":"c000e7s4","timedate":"2012-12-10 22:08:06","lat":"37.7563","lon":"143.7503","magnitude":"4.8","depth":"44.30","region":"off the east coast of Honshu, Japan"},{"src":"us","eqid":"c000e7p4","timedate":"2012-12-10 20:47:50","lat":"-6.4853","lon":"129.9174","magnitude":"5.3","depth":"166.50","region":"Banda Sea"},{"src":"us","eqid":"c000e7j7","timedate":"2012-12-10 16:56:56","lat":"44.9560","lon":"37.5585","magnitude":"4.9","depth":"33.00","region":"Caucasus region, Russia"},{"src":"us","eqid":"c000e7j6","timedate":"2012-12-10 16:53:09","lat":"-6.5403","lon":"129.8146","magnitude":"7.1","depth":"159.30","region":"Banda Sea"},{"src":"us","eqid":"2012izap","timedate":"2012-12-10 16:27:40","lat":"2.6482","lon":"95.4902","magnitude":"4.3","depth":"41.20","region":"Simeulue, Indonesia"},{"src":"us","eqid":"2012izan","timedate":"2012-12-10 16:09:41","lat":"-15.5437","lon":"-72.8551","magnitude":"4.3","depth":"36.50","region":"southern Peru"},{"src":"us","eqid":"2012izai","timedate":"2012-12-10 15:25:46","lat":"-38.9428","lon":"-72.9128","magnitude":"4.8","depth":"29.70","region":"Araucania, Chile"},{"src":"us","eqid":"c000e7h4","timedate":"2012-12-10 12:52:23","lat":"14.7635","lon":"-92.5381","magnitude":"4.3","depth":"78.40","region":"offshore Chiapas, Mexico"},{"src":"us","eqid":"c000e7h2","timedate":"2012-12-10 12:43:24","lat":"37.5750","lon":"143.5546","magnitude":"4.6","depth":"34.20","region":"off the east coast of Honshu, Japan"},{"src":"us","eqid":"c000e7gd","timedate":"2012-12-10 11:11:44","lat":"37.9380","lon":"143.7370","magnitude":"4.4","depth":"36.60","region":"off the east coast of Honshu, Japan"},{"src":"us","eqid":"c000e7f3","timedate":"2012-12-10 09:09:35","lat":"37.7940","lon":"143.6077","magnitude":"4.9","depth":"30.50","region":"off the east coast of Honshu, Japan"},{"src":"us","eqid":"c000e7et","timedate":"2012-12-10 08:41:41","lat":"32.2551","lon":"141.3006","magnitude":"4.7","depth":"7.00","region":"Izu Islands, Japan region"},{"src":"us","eqid":"c000e79z","timedate":"2012-12-10 00:09:53","lat":"37.6843","lon":"143.7541","magnitude":"4.8","depth":"33.90","region":"off the east coast of Honshu, Japan"},{"src":"us","eqid":"c000e79j","timedate":"2012-12-09 23:56:36","lat":"37.5019","lon":"143.8313","magnitude":"4.9","depth":"34.00","region":"off the east coast of Honshu, Japan"},{"src":"us","eqid":"c000e78y","timedate":"2012-12-09 23:50:35","lat":"37.4576","lon":"143.7809","magnitude":"5.0","depth":"37.90","region":"off the east coast of Honshu, Japan"},{"src":"us","eqid":"c000e78g","timedate":"2012-12-09 23:13:21","lat":"1.6247","lon":"89.6071","magnitude":"4.7","depth":"14.70","region":"North Indian Ocean"},{"src":"us","eqid":"c000e75p","timedate":"2012-12-09 21:45:34","lat":"6.7185","lon":"126.1836","magnitude":"5.6","depth":"56.00","region":"Mindanao, Philippines"},{"src":"us","eqid":"c000e74n","timedate":"2012-12-09 20:52:38","lat":"-16.1553","lon":"-174.2240","magnitude":"5.2","depth":"129.70","region":"Tonga"},{"src":"us","eqid":"c000e73h","timedate":"2012-12-09 19:09:32","lat":"52.4480","lon":"-170.0712","magnitude":"4.8","depth":"48.30","region":"Fox Islands, Aleutian Islands, Alaska"},{"src":"us","eqid":"c000e73b","timedate":"2012-12-09 18:59:48","lat":"37.9142","lon":"143.9130","magnitude":"4.9","depth":"35.00","region":"off the east coast of Honshu, Japan"},{"src":"us","eqid":"c000e72x","timedate":"2012-12-09 18:30:07","lat":"-3.6442","lon":"141.1098","magnitude":"5.2","depth":"58.40","region":"New Guinea, Papua New Guinea"},{"src":"us","eqid":"2012iyaq","timedate":"2012-12-09 14:42:17","lat":"37.7446","lon":"143.9782","magnitude":"4.8","depth":"34.20","region":"off the east coast of Honshu, Japan"},{"src":"us","eqid":"c000e70r","timedate":"2012-12-09 12:38:40","lat":"-54.0382","lon":"-1.9409","magnitude":"5.0","depth":"9.90","region":"Bouvet Island region"},{"src":"us","eqid":"c000e70f","timedate":"2012-12-09 11:47:04","lat":"38.1723","lon":"143.7486","magnitude":"4.6","depth":"34.80","region":"off the east coast of Honshu, Japan"},{"src":"us","eqid":"c000e6yy","timedate":"2012-12-09 06:03:18","lat":"9.9053","lon":"-83.9302","magnitude":"4.5","depth":"24.30","region":"Costa Rica"},{"src":"us","eqid":"c000e6xw","timedate":"2012-12-09 03:09:49","lat":"29.2344","lon":"139.3552","magnitude":"4.3","depth":"389.80","region":"Izu Islands, Japan region"},{"src":"us","eqid":"c000e6xn","timedate":"2012-12-09 02:50:51","lat":"-3.5022","lon":"145.3572","magnitude":"4.9","depth":"34.00","region":"near the north coast of New Guinea, Papua New Guinea"},{"src":"us","eqid":"c000e6xb","timedate":"2012-12-09 02:34:19","lat":"37.7906","lon":"143.5902","magnitude":"5.3","depth":"30.00","region":"off the east coast of Honshu, Japan"},{"src":"us","eqid":"c000e6wm","timedate":"2012-12-09 01:23:07","lat":"37.8954","lon":"22.6208","magnitude":"4.5","depth":"13.90","region":"southern Greece"},{"src":"us","eqid":"c000e6w9","timedate":"2012-12-09 00:14:07","lat":"27.9562","lon":"57.3689","magnitude":"4.3","depth":"10.10","region":"southern Iran"},{"src":"us","eqid":"c000e6vw","timedate":"2012-12-08 23:44:11","lat":"13.8750","lon":"-91.8201","magnitude":"4.4","depth":"35.20","region":"offshore Guatemala"},{"src":"us","eqid":"c000e6u3","timedate":"2012-12-08 21:46:08","lat":"-14.7775","lon":"167.2197","magnitude":"4.8","depth":"134.90","region":"Vanuatu"},{"src":"us","eqid":"c000e6rx","timedate":"2012-12-08 20:47:24","lat":"-5.1721","lon":"102.2701","magnitude":"4.7","depth":"28.90","region":"southern Sumatra, Indonesia"},{"src":"us","eqid":"c000e6nx","timedate":"2012-12-08 19:00:11","lat":"-7.1925","lon":"144.0014","magnitude":"5.1","depth":"32.80","region":"near the south coast of New Guinea, Papua New Guinea"},{"src":"us","eqid":"c000e6nx","timedate":"2012-12-08 19:00:11","lat":"-7.1925","lon":"144.0014","magnitude":"5.1","depth":"32.80","region":"near the south coast of New Guinea, Papua New Guinea"},{"src":"us","eqid":"c000e6my","timedate":"2012-12-08 18:49:25","lat":"17.2960","lon":"-100.1136","magnitude":"4.1","depth":"49.20","region":"Guerrero, Mexico"},{"src":"us","eqid":"c000e6lb","timedate":"2012-12-08 16:35:17","lat":"-7.2106","lon":"143.9290","magnitude":"5.7","depth":"10.70","region":"near the south coast of New Guinea, Papua New Guinea"},{"src":"us","eqid":"c000e6j6","timedate":"2012-12-08 14:26:55","lat":"25.7532","lon":"122.3356","magnitude":"5.0","depth":"289.10","region":"Taiwan region"},{"src":"us","eqid":"c000e6it","timedate":"2012-12-08 13:53:37","lat":"37.7683","lon":"143.9552","magnitude":"4.7","depth":"34.70","region":"off the east coast of Honshu, Japan"},{"src":"us","eqid":"c000e6hn","timedate":"2012-12-08 12:50:10","lat":"37.6227","lon":"143.5686","magnitude":"4.9","depth":"35.00","region":"off the east coast of Honshu, Japan"},{"src":"us","eqid":"c000e6gk","timedate":"2012-12-08 10:27:31","lat":"-7.1449","lon":"144.0484","magnitude":"5.0","depth":"33.60","region":"near the south coast of New Guinea, Papua New Guinea"},{"src":"us","eqid":"c000e6gj","timedate":"2012-12-08 10:09:41","lat":"38.1239","lon":"74.1600","magnitude":"4.7","depth":"157.60","region":"Tajikistan"},{"src":"us","eqid":"c000e6f7","timedate":"2012-12-08 08:11:56","lat":"2.5709","lon":"128.3679","magnitude":"5.0","depth":"153.90","region":"Halmahera, Indonesia"},{"src":"us","eqid":"c000e6eh","timedate":"2012-12-08 07:18:13","lat":"37.8335","lon":"143.8836","magnitude":"4.7","depth":"35.20","region":"off the east coast of Honshu, Japan"},{"src":"us","eqid":"c000e6er","timedate":"2012-12-08 07:06:12","lat":"23.0268","lon":"70.3065","magnitude":"4.0","depth":"22.00","region":"Gujarat, India"},{"src":"us","eqid":"c000e6dh","timedate":"2012-12-08 06:16:55","lat":"-7.2479","lon":"143.9304","magnitude":"5.1","depth":"21.70","region":"near the south coast of New Guinea, Papua New Guinea"},{"src":"us","eqid":"c000e6c8","timedate":"2012-12-08 02:26:14","lat":"37.4078","lon":"143.8623","magnitude":"4.4","depth":"30.00","region":"off the east coast of Honshu, Japan"},{"src":"us","eqid":"c000e6bh","timedate":"2012-12-08 02:12:52","lat":"37.6040","lon":"143.7923","magnitude":"4.7","depth":"30.50","region":"off the east coast of Honshu, Japan"},{"src":"us","eqid":"c000e6b7","timedate":"2012-12-08 00:30:30","lat":"16.6545","lon":"-97.2036","magnitude":"4.0","depth":"10.10","region":"Oaxaca, Mexico"},{"src":"us","eqid":"c000e6b7","timedate":"2012-12-08 00:30:30","lat":"16.6545","lon":"-97.2036","magnitude":"4.0","depth":"10.10","region":"Oaxaca, Mexico"},{"src":"us","eqid":"c000e6b2","timedate":"2012-12-08 00:08:17","lat":"37.9211","lon":"143.8414","magnitude":"4.8","depth":"10.70","region":"off the east coast of Honshu, Japan"},{"src":"us","eqid":"c000e6au","timedate":"2012-12-07 23:52:04","lat":"12.6849","lon":"-87.8683","magnitude":"4.5","depth":"69.60","region":"near the coast of Nicaragua"},{"src":"us","eqid":"c000e6a7","timedate":"2012-12-07 23:00:02","lat":"37.7322","lon":"143.8633","magnitude":"5.6","depth":"34.20","region":"off the east coast of Honshu, Japan"},{"src":"us","eqid":"c000e67v","timedate":"2012-12-07 21:36:37","lat":"37.7272","lon":"143.5680","magnitude":"4.8","depth":"27.60","region":"off the east coast of Honshu, Japan"},{"src":"us","eqid":"c000e66v","timedate":"2012-12-07 21:20:52","lat":"37.4373","lon":"143.9005","magnitude":"4.7","depth":"40.80","region":"off the east coast of Honshu, Japan"},{"src":"us","eqid":"c000e65q","timedate":"2012-12-07 21:01:12","lat":"37.4466","lon":"143.6539","magnitude":"4.9","depth":"21.70","region":"off the east coast of Honshu, Japan"},{"src":"us","eqid":"c000e64a","timedate":"2012-12-07 20:30:39","lat":"37.7959","lon":"143.6032","magnitude":"4.9","depth":"25.50","region":"off the east coast of Honshu, Japan"},{"src":"us","eqid":"c000e64i","timedate":"2012-12-07 20:07:15","lat":"18.3574","lon":"-102.4666","magnitude":"4.2","depth":"70.60","region":"Michoacan, Mexico"},{"src":"us","eqid":"c000e62j","timedate":"2012-12-07 19:50:21","lat":"-7.6329","lon":"146.9626","magnitude":"5.6","depth":"118.90","region":"eastern New Guinea region, Papua New Guinea"},{"src":"us","eqid":"c000e61w","timedate":"2012-12-07 19:25:00","lat":"40.8805","lon":"142.8178","magnitude":"4.9","depth":"38.50","region":"near the east coast of Honshu, Japan"},{"src":"us","eqid":"c000e5z5","timedate":"2012-12-07 18:19:07","lat":"-38.3207","lon":"176.0857","magnitude":"6.3","depth":"166.80","region":"North Island of New Zealand"},{"src":"us","eqid":"c000e5wi","timedate":"2012-12-07 16:18:42","lat":"37.7070","lon":"143.8775","magnitude":"5.0","depth":"32.60","region":"off the east coast of Honshu, Japan"},{"src":"us","eqid":"c000e5wa","timedate":"2012-12-07 16:11:56","lat":"37.8099","lon":"143.7406","magnitude":"4.7","depth":"34.90","region":"off the east coast of Honshu, Japan"},{"src":"us","eqid":"c000e5w6","timedate":"2012-12-07 16:01:54","lat":"37.7230","lon":"143.8680","magnitude":"5.1","depth":"30.70","region":"off the east coast of Honshu, Japan"},{"src":"us","eqid":"c000e5vd","timedate":"2012-12-07 15:15:31","lat":"37.8000","lon":"143.8504","magnitude":"5.0","depth":"35.80","region":"off the east coast of Honshu, Japan"},{"src":"us","eqid":"c000e5uw","timedate":"2012-12-07 14:32:17","lat":"37.7620","lon":"143.6370","magnitude":"4.7","depth":"35.00","region":"off the east coast of Honshu, Japan"},{"src":"us","eqid":"c000e5ug","timedate":"2012-12-07 14:08:43","lat":"38.7454","lon":"88.1013","magnitude":"5.3","depth":"16.10","region":"southern Xinjiang, China"},{"src":"us","eqid":"c000e5tq","timedate":"2012-12-07 12:58:07","lat":"37.8774","lon":"143.6626","magnitude":"5.0","depth":"34.90","region":"off the east coast of Honshu, Japan"},{"src":"us","eqid":"c000e5th","timedate":"2012-12-07 12:48:51","lat":"37.5345","lon":"143.7154","magnitude":"4.8","depth":"35.10","region":"off the east coast of Honshu, Japan"},{"src":"us","eqid":"c000e5td","timedate":"2012-12-07 12:33:37","lat":"37.5552","lon":"143.6509","magnitude":"4.7","depth":"34.90","region":"off the east coast of Honshu, Japan"},{"src":"us","eqid":"c000e5t1","timedate":"2012-12-07 12:05:27","lat":"37.8527","lon":"143.7351","magnitude":"5.0","depth":"35.00","region":"off the east coast of Honshu, Japan"},{"src":"us","eqid":"c000e5rx","timedate":"2012-12-07 09:56:27","lat":"37.5717","lon":"143.7749","magnitude":"4.6","depth":"35.00","region":"off the east coast of Honshu, Japan"},{"src":"us","eqid":"c000e5r9","timedate":"2012-12-07 09:39:46","lat":"28.1199","lon":"-111.9796","magnitude":"4.1","depth":"15.30","region":"Gulf of California"},{"src":"us","eqid":"c000e5qz","timedate":"2012-12-07 09:23:04","lat":"37.8222","lon":"144.1752","magnitude":"4.8","depth":"35.10","region":"off the east coast of Honshu, Japan"},{"src":"us","eqid":"c000e5qg","timedate":"2012-12-07 09:13:23","lat":"37.7215","lon":"143.7460","magnitude":"4.7","depth":"35.10","region":"off the east coast of Honshu, Japan"},{"src":"us","eqid":"c000e5pw","timedate":"2012-12-07 09:01:53","lat":"37.7408","lon":"143.5427","magnitude":"4.7","depth":"35.30","region":"off the east coast of Honshu, Japan"}]}
